tfviz/__init__.py
tfviz/callback.py
tfviz/config.py
tfviz/metrics.py
tfviz/visualizer.py
tfviz-1.0.0.dist-info/licenses/LICENSE
tfviz-1.0.0.dist-info/METADATA
tfviz-1.0.0.dist-info/WHEEL
tfviz-1.0.0.dist-info/top_level.txt
tfviz-1.0.0.dist-info/RECORD
