Metadata-Version: 2.4
Name: tfviz
Version: 1.0.0
Summary: Real-time visualization for TensorFlow training metrics
Home-page: https://github.com/DeepPythonist/TFViz
Author: Mohammad Rasol Esfandiari
Author-email: Mohammad Rasol Esfandiari <Mrasolesfandiari@gmail.com>
License: MIT
Project-URL: Homepage, https://github.com/DeepPythonist/TFViz
Project-URL: Repository, https://github.com/DeepPythonist/TFViz
Project-URL: Issues, https://github.com/DeepPythonist/TFViz/issues
Keywords: tensorflow,visualization,machine-learning,plotting,metrics
Classifier: Development Status :: 4 - Beta
Classifier: Intended Audience :: Developers
Classifier: License :: OSI Approved :: MIT License
Classifier: Operating System :: OS Independent
Classifier: Programming Language :: Python :: 3
Classifier: Programming Language :: Python :: 3.7
Classifier: Programming Language :: Python :: 3.8
Classifier: Programming Language :: Python :: 3.9
Classifier: Programming Language :: Python :: 3.10
Classifier: Programming Language :: Python :: 3.11
Classifier: Programming Language :: Python :: 3.12
Classifier: Topic :: Scientific/Engineering :: Artificial Intelligence
Classifier: Topic :: Software Development :: Libraries :: Python Modules
Requires-Python: >=3.7
License-File: LICENSE
Requires-Dist: tensorflow>=2.0.0
Requires-Dist: matplotlib>=3.0.0
Requires-Dist: numpy>=1.15.0
Provides-Extra: dev
Requires-Dist: pytest>=6.0; extra == "dev"
Requires-Dist: black>=21.0; extra == "dev"
Requires-Dist: flake8>=3.8; extra == "dev"
Dynamic: author
Dynamic: home-page
Dynamic: license-file
Dynamic: requires-python
